szkopulpylib/__init__.py
szkopulpylib/szkopul.py
szkopulpylib-0.0.1.dist-info/METADATA
szkopulpylib-0.0.1.dist-info/WHEEL
szkopulpylib-0.0.1.dist-info/top_level.txt
szkopulpylib-0.0.1.dist-info/RECORD
